awesomediff/__init__.py
awesomediff/core.py
awesomediff/func.py
awesomediff/solvers.py
tests/__init__.py
tests/test_evaluate.py
tests/test_function_methods.py
tests/test_functions.py
tests/test_solvers.py
tests/test_variable_methods.py
awesomediff_test-1.0.0.dist-info/LICENSE.txt
awesomediff_test-1.0.0.dist-info/METADATA
awesomediff_test-1.0.0.dist-info/WHEEL
awesomediff_test-1.0.0.dist-info/top_level.txt
awesomediff_test-1.0.0.dist-info/RECORD
