Metadata-Version: 2.1
Name: awesomediff-test
Version: 1.0.0
Summary: A package for automatic differentiation
Home-page: https://github.com/awesomediff/cs207-FinalProject
Author: Claire
Author-email: author@example.com
License: UNKNOWN
Platform: UNKNOWN
Classifier: Programming Language :: Python :: 3
Classifier: License :: OSI Approved :: MIT License
Classifier: Operating System :: OS Independent
Requires-Python: >=3.6
